{
  "preguntas": [
    {
      "texto": "¿Quién se acabaría toda la botana si pudiera?",
      "intensidad": 1
    },
    {
      "texto": "¿Quién se despertaría primero para preparales el desayuno a todos?",
      "intensidad": 1
    },
    {
      "texto": "¿Quién es mas aesthetic?",
      "intensidad": 1
    },
    {
      "texto": "¿Quién es el más quejumbroso de los presentes?",
      "intensidad": 1
    },
    {
      "texto": "¿Quién es el más irresponsable?",
      "intensidad": 1
    },
    {
      "texto": "¿Quién es el más terco?",
      "intensidad": 1
    },
    {
      "texto": "¿A quién se le olvidaría la cartulina?",
      "intensidad": 1
    },
    {
      "texto": "¿Quién es el más justo?",
      "intensidad": 1
    },
    {
      "texto": "¿Quién es el más impulsivo?",
      "intensidad": 1
    },
    {
      "texto": "¿Quién sería el jefe del grupo?",
      "intensidad": 1
    },
    {
      "texto": "¿Quién seria el primero en aventarse a un pozo?",
      "intensidad": 1
    },
    {
      "texto": "¿Quién es más propenso a llorar en una pelicula?",
      "intensidad": 1
    },
    {
      "texto": "¿Quién es el mas antojadizo / gusguero?",
      "intensidad": 1
    },
    {
      "texto": "¿Quién es el mas dormilón?",
      "intensidad": 1
    },
    {
      "texto": "¿Quién es el más doble cara?",
      "intensidad": 1
    },
    {
      "texto": "¿Quién siempre gana los debates?",
      "intensidad": 1
    },
    {
      "texto": "¿Quién debió estudiar derecho?",
      "intensidad": 1
    },
    {
      "texto": "¿Quién es más contestón?",
      "intensidad": 1
    },
    {
      "texto": "¿Quién podria fluir en cualquier escenario?",
      "intensidad": 1
    },
    {
      "texto": "¿Quién es el centro de atención?",
      "intensidad": 1
    },
    {
      "texto": "¿Quién es el alma de la fiesta?",
      "intensidad": 1
    },
    {
      "texto": "¿Quien es el más peleonero?",
      "intensidad": 1
    },
    {
      "texto": "¿Quién es el más espiritual?",
      "intensidad": 1
    },
    {
      "texto": "¿Quién es el más inteligente?",
      "intensidad": 1
    },
    {
      "texto": "¿Quién tiene los mejores modales?",
      "intensidad": 1
    },
    {
      "texto": "¿Quién siempre corrige al otro cuando está haciendo algo mal?",
      "intensidad": 1
    },
    {
      "texto": "¿Quién es la \"mamá\" del grupo?",
      "intensidad": 1
    },
    {
      "texto": "¿Quién podria ganar un premio nobel?",
      "intensidad": 1
    },
    {
      "texto": "¿Quién haría lo que sea por dinero?",
      "intensidad": 1
    },
    {
      "texto": "¿Quién se lleva y no aguanta?",
      "intensidad": 1
    },
    {
      "texto": "¿Quién es el más entregado del grupo?",
      "intensidad": 1
    },
    {
      "texto": "¿Quién es el que nunca termina sus proyectos personales?",
      "intensidad": 1
    },
    {
      "texto": "¿Quién tiene su sexto sentido más desarrollado?",
      "intensidad": 1
    },
    {
      "texto": "¿Quién es el más viajero?",
      "intensidad": 1
    },
    {
      "texto": "¿Quién es el más curioso?",
      "intensidad": 1
    },
    {
      "texto": "¿Quién es el más directo?",
      "intensidad": 1
    },
    {
      "texto": "¿Quién es el más honesto?",
      "intensidad": 1
    },
    {
      "texto": "¿Quién es más común que se disosie a media conversación?",
      "intensidad": 1
    },
    {
      "texto": "¿Quién es el mas chismoso del grupo?",
      "intensidad": 1
    },
    {
      "texto": "¿Quién es el mejor guardando secretos?",
      "intensidad": 1
    },
    {
      "texto": "¿Quién es el más ecológico?",
      "intensidad": 1
    },
    {
      "texto": "¿Quién es el más soñador?",
      "intensidad": 1
    },
    {
      "texto": "¿Quién es el más empatico?",
      "intensidad": 1
    },
    {
      "texto": "¿Quién podría ser pirómano del grupo?",
      "intensidad": 1
    },
    {
      "texto": "¿Quién es más adicto a comprar cosas por internet?",
      "intensidad": 1
    },
    {
      "texto": "¿Quién no respondería el teléfono pasando las 12 am?",
      "intensidad": 1
    },
    {
      "texto": "¿Quién compraría un vuelo impulsivamente?",
      "intensidad": 1
    },
    {
      "texto": "¿Quién es más propenso a acabarse su trago primero?",
      "intensidad": 1
    },
    {
      "texto": "¿Quién invitaría los tragos?",
      "intensidad": 1
    },
    {
      "texto": "¿Quién viajaría kilómetros para ir a ver a alguien?",
      "intensidad": 1
    },
    {
      "texto": "¿Quién se aventaría de un paracaídas?",
      "intensidad": 1
    },
    {
      "texto": "¿Quién mentiría para safarse de un compromiso?",
      "intensidad": 1
    },
    {
      "texto": "¿Quién rescataría a un animalito de la calle?",
      "intensidad": 1
    },
    {
      "texto": "¿Quién es más indeciso?",
      "intensidad": 1
    },
    {
      "texto": "¿Quién es el más pesimista?",
      "intensidad": 1
    },
    {
      "texto": "¿Quién es más leal?",
      "intensidad": 1
    },
    {
      "texto": "¿Quién sería el asesino si esta fuera una película de terror?",
      "intensidad": 1
    },
    {
      "texto": "¿Quién tiene la sonrisa más bonita?",
      "intensidad": 1
    },
    {
      "texto": "¿Quién es el más madrugador?",
      "intensidad": 1
    },
    {
      "texto": "¿Quién es el más fiestero?",
      "intensidad": 1
    },
    {
      "texto": "¿Quién podría volverse influencer?",
      "intensidad": 1
    },
    {
      "texto": "¿Quién es el más ahorrador?",
      "intensidad": 1
    },
    {
      "texto": "¿Quién se duerme primero?",
      "intensidad": 1
    },
    {
      "texto": "¿Quién ronca más fuerte al dormir?",
      "intensidad": 1
    },
    {
      "texto": "¿Quién habla dormido?",
      "intensidad": 1
    },
    {
      "texto": "¿Quién ha ido a más conciertos?",
      "intensidad": 1
    },
    {
      "texto": "¿Quién maneja mejor las crisis existenciales?",
      "intensidad": 1
    },
    {
      "texto": "¿Quién es el más chefcito?",
      "intensidad": 1
    },
    {
      "texto": "¿A quién de aquí le cuesta mucho mentir?",
      "intensidad": 1
    },
    {
      "texto": "¿Quién cocinaría sin sazón?",
      "intensidad": 1
    },
    {
      "texto": "¿Quién fue el más popular en la escuela?",
      "intensidad": 1
    },
    {
      "texto": "¿Quién sería el primero en volverse hippie?",
      "intensidad": 1
    },
    {
      "texto": "¿Quién podría ser locutor de radio?",
      "intensidad": 1
    },
    {
      "texto": "¿Quién arma los planes para juntarse?",
      "intensidad": 1
    },
    {
      "texto": "¿Quién es el más carrilla?",
      "intensidad": 1
    },
    {
      "texto": "¿Quién es el más intuitivo?",
      "intensidad": 1
    },
    {
      "texto": "¿Quién se burla de sus propias desgracias?",
      "intensidad": 1
    },
    {
      "texto": "¿Quién prefiere quedarse en su casa?",
      "intensidad": 1
    },
    {
      "texto": "¿Quién inicaría una conversación con algún extraño?",
      "intensidad": 1
    },
    {
      "texto": "¿Quién tiene cara de cero amigos?",
      "intensidad": 1
    },
    {
      "texto": "¿Quién podría perderse en una ciudad nueva?",
      "intensidad": 1
    },
    {
      "texto": "¿Quién podría terminar en una fiesta sin invitación?",
      "intensidad": 1
    },
    {
      "texto": "¿Quién se caería en público?",
      "intensidad": 1
    },
    {
      "texto": "¿Quién se reiría porque otro se está riendo?",
      "intensidad": 1
    },
    {
      "texto": "¿Quién olvidaría lo que esta diciendo en medio de la conversación?",
      "intensidad": 1
    },
    {
      "texto": "¿Quién empujaría una puerta que dice jale?",
      "intensidad": 1
    },
    {
      "texto": "¿Quién intentaría hablar con los animales imitando sus sonidos?",
      "intensidad": 1
    },
    {
      "texto": "¿Quién podría olvidar dónde dejo algo que trae justo en la mano?",
      "intensidad": 1
    },
    {
      "texto": "¿Quién hace gestos expresivos que delatan lo que piensa?",
      "intensidad": 1
    },
    {
      "texto": "¿Quién podría confundir a un extraño con alguien que conoce?",
      "intensidad": 1
    },
    {
      "texto": "¿Quién es más probable que pierda las llaves?",
      "intensidad": 1
    },
    {
      "texto": "¿Quién se reiría fuerte en un momento no apropiado?",
      "intensidad": 1
    },
    {
      "texto": "¿Quién tiene las historias más rándom?",
      "intensidad": 1
    },
    {
      "texto": "¿Quién se levantaría de madrugada para buscar algo en el refrigerador?",
      "intensidad": 1
    },
    {
      "texto": "¿Quién le cuesta decir que no?",
      "intensidad": 1
    },
    {
      "texto": "¿Quién se levantaría de madrugada con la intención de ver el amanecer?",
      "intensidad": 1
    },
    {
      "texto": "¿Quién es más probable que no duerma por terminar de ver una serie?",
      "intensidad": 1
    },
    {
      "texto": "¿Quién es más probable que adopte muchos perritos?",
      "intensidad": 1
    },
    {
      "texto": "¿Quién es más probable que no pueda cuidar ni a un cactus?",
      "intensidad": 1
    },
    {
      "texto": "¿Quién podría no estudiar para un examen y sacar 10?",
      "intensidad": 1
    },
    {
      "texto": "¿Quién podría comer Maruchan toda la semana para poder ir a un concierto?",
      "intensidad": 1
    },
    {
      "texto": "¿Quién se volvería trepador de cerros por una ruptura amorosa?",
      "intensidad": 1
    },
    {
      "texto": "¿Quién se postularía para la presidencia?",
      "intensidad": 1
    },
    {
      "texto": "¿Quién se sabe todas las canciones de señora?",
      "intensidad": 1
    },
    {
      "texto": "¿Quién podría ser presidente del país?",
      "intensidad": 1
    },
    {
      "texto": "¿Quién se iría a pistear con otra mesa?",
      "intensidad": 2
    },
    {
      "texto": "¿Quién se realizaría una cirugía estética?",
      "intensidad": 2
    },
    {
      "texto": "¿Quién caería en una estafa?",
      "intensidad": 2
    },
    {
      "texto": "¿Quién entraría en un negocio piramidal?",
      "intensidad": 2
    },
    {
      "texto": "¿Quién mentiría sobre su signo zodiacal para quedar bien en una cita?",
      "intensidad": 2
    },
    {
      "texto": "¿Quién tendria una cuenta falsa en redes sociales?",
      "intensidad": 2
    },
    {
      "texto": "¿Quién haría drag?",
      "intensidad": 2
    },
    {
      "texto": "¿Quién es más miedoso?",
      "intensidad": 2
    },
    {
      "texto": "¿Quién crees que tenga la ropa interior más rota?",
      "intensidad": 2
    },
    {
      "texto": "¿Quién sería poseído jugando a la ouija?",
      "intensidad": 2
    },
    {
      "texto": "¿Quién tuvo su primer beso primero?",
      "intensidad": 2
    },
    {
      "texto": "¿Quién es ridículamente optimista?",
      "intensidad": 2
    },
    {
      "texto": "¿Quién podría tener una sugar mommy?",
      "intensidad": 2
    },
    {
      "texto": "¿Quién podría ser un sugar daddy?",
      "intensidad": 2
    },
    {
      "texto": "¿Quién es el mas borracho del grupo?",
      "intensidad": 2
    },
    {
      "texto": "¿Quién le tiene miedo al compromiso?",
      "intensidad": 2
    },
    {
      "texto": "¿Quién podría estar pasándola mal y nadie se enteraría nunca?",
      "intensidad": 2
    },
    {
      "texto": "¿Quién no tiene responsabilidad afectiva?",
      "intensidad": 2
    },
    {
      "texto": "¿Quién podria tener TDAH?",
      "intensidad": 2
    },
    {
      "texto": "¿Quién es más propenso a ser corrido del antro?",
      "intensidad": 2
    },
    {
      "texto": "¿Quién es el mas sexoso/ pervertido?",
      "intensidad": 2
    },
    {
      "texto": "¿Quién podria ser un asesino serial?",
      "intensidad": 2
    },
    {
      "texto": "¿Quién es el más vengativo?",
      "intensidad": 2
    },
    {
      "texto": "¿Quién es mas propenso a meterse en una pelea?",
      "intensidad": 2
    },
    {
      "texto": "¿Quién sería descubierto en una orgía en un parque?",
      "intensidad": 2
    },
    {
      "texto": "¿Quién perdió la virginidad antes que todos?",
      "intensidad": 2
    },
    {
      "texto": "¿Quién haría un trio?",
      "intensidad": 2
    },
    {
      "texto": "¿Quién evade más sus emociones?",
      "intensidad": 2
    },
    {
      "texto": "¿Quién extraña a su ex?",
      "intensidad": 2
    },
    {
      "texto": "¿Quién odia a su ex?",
      "intensidad": 2
    },
    {
      "texto": "¿Quién es más vengativo?",
      "intensidad": 2
    },
    {
      "texto": "¿Quién es el más drama queen?",
      "intensidad": 2
    },
    {
      "texto": "¿Quién es el/la mas toxic@?",
      "intensidad": 2
    },
    {
      "texto": "¿Quién es el/la más simp (mandilón/mandilona)?",
      "intensidad": 2
    },
    {
      "texto": "¿Quién es más propenso a regresar con su ex?",
      "intensidad": 2
    },
    {
      "texto": "¿Quién sería el primero en romper una ley?",
      "intensidad": 2
    },
    {
      "texto": "¿Quién acabaría en la cárcel por algo que no hizo?",
      "intensidad": 2
    },
    {
      "texto": "¿Quién se pierde con todo y Google Maps?",
      "intensidad": 2
    },
    {
      "texto": "¿Quién se besaría con todos los del grupo si pudiera?",
      "intensidad": 2
    },
    {
      "texto": "¿Quién es quien más trapea el piso con las nalgas (quién perrea más)?",
      "intensidad": 2
    },
    {
      "texto": "¿Quién sabría dónde esconder un cadaver?",
      "intensidad": 2
    },
    {
      "texto": "¿Quién podría ser un espía?",
      "intensidad": 2
    },
    {
      "texto": "¿Quién eligió la carrera equivocada?",
      "intensidad": 2
    },
    {
      "texto": "¿Quién es el más fuckboy/fuckgirl?",
      "intensidad": 2
    },
    {
      "texto": "¿Quién es más propenso a desmayarse en un juego mecánico?",
      "intensidad": 2
    },
    {
      "texto": "¿Quién siempre pide prestado?",
      "intensidad": 2
    },
    {
      "texto": "¿Quién es una mala influencia?",
      "intensidad": 2
    },
    {
      "texto": "¿Quién parece un santo, pero es una mala influencia?",
      "intensidad": 2
    },
    {
      "texto": "¿Quién perdonaría una infidelidad?",
      "intensidad": 2
    },
    {
      "texto": "¿Quién dice que no toma pero manda mensaje para la peda?",
      "intensidad": 2
    },
    {
      "texto": "¿Quién es más probable que temine soltero toda su vida?",
      "intensidad": 2
    },
    {
      "texto": "¿Quién fue un bully en la escuela?",
      "intensidad": 2
    },
    {
      "texto": "¿Quién nunca responde los mensajes?",
      "intensidad": 2
    },
    {
      "texto": "¿Quién se puede tomar 100 fotos y ninguna le convencerá?",
      "intensidad": 2
    },
    {
      "texto": "¿Quién podría hacer un split?",
      "intensidad": 2
    },
    {
      "texto": "¿Quién es más enojón?",
      "intensidad": 2
    },
    {
      "texto": "¿Quién sería arrestado por algo absurdo?",
      "intensidad": 2
    },
    {
      "texto": "¿Quién de aquí es más rencoroso?",
      "intensidad": 2
    },
    {
      "texto": "¿Quién es más propenso a contagiarse de clamidia de koala?",
      "intensidad": 2
    },
    {
      "texto": "¿Quién aceptaría una cita por comida gratis?",
      "intensidad": 2
    },
    {
      "texto": "¿Quién haría un viaje sin decirle a nadie?",
      "intensidad": 2
    },
    {
      "texto": "¿Quién sería más exitoso como líder de secta?",
      "intensidad": 2
    },
    {
      "texto": "¿Quién es más pedorro?",
      "intensidad": 2
    },
    {
      "texto": "¿Quién es más egocéntrico?",
      "intensidad": 2
    },
    {
      "texto": "¿Quién es el más alburero?",
      "intensidad": 2
    },
    {
      "texto": "¿Quién tendría un animal exótico de mascota?",
      "intensidad": 2
    },
    {
      "texto": "¿Quién siempre liga aunque no quiera?",
      "intensidad": 2
    },
    {
      "texto": "¿Quién terminaría la cita porque su signo zodiacal no es compatible?",
      "intensidad": 3
    },
    {
      "texto": "¿Quién ha besado más bocas hasta el momento?",
      "intensidad": 3
    },
    {
      "texto": "¿Quién es más probable que baile en una salida para ganar una botella?",
      "intensidad": 3
    },
    {
      "texto": "¿Quién podría terminar bailando sobre una mesa?",
      "intensidad": 3
    },
    {
      "texto": "¿Quién saldría con el/la ex de un amigo?",
      "intensidad": 3
    },
    {
      "texto": "¿Quién besaría a un desconocido en una fiesta?",
      "intensidad": 3
    },
    {
      "texto": "¿Quién aparece cuando necesita algo más que sólo amistad?",
      "intensidad": 3
    },
    {
      "texto": "¿Quién de aqui ha prolongado más su relación tóxica?",
      "intensidad": 3
    },
    {
      "texto": "¿Quién es más probable que termine en un manicomio?",
      "intensidad": 3
    },
    {
      "texto": "¿Quién pagaría con cuerpo si se queda sin dinero?",
      "intensidad": 3
    },
    {
      "texto": "¿Quién es el más celoso?",
      "intensidad": 3
    },
    {
      "texto": "¿Quién sería la tabla del 1 (por ser é/la más fácil)?",
      "intensidad": 3
    },
    {
      "texto": "¿Quién sería el semen (sino sale con una jalada, sale con una mamada)?",
      "intensidad": 3
    },
    {
      "texto": "¿Quién lo tiene más grande?",
      "intensidad": 3
    },
    {
      "texto": "¿Quién las tiene más grandes?",
      "intensidad": 3
    },
    {
      "texto": "¿Quién podría tener sexo en una iglesia?",
      "intensidad": 3
    },
    {
      "texto": "¿Quién crees que haya tenido más parejas sexuales?",
      "intensidad": 3
    },
    {
      "texto": "¿Quién es más propenso a tener más juguetes sexuales?",
      "intensidad": 3
    },
    {
      "texto": "¿Quién podría tener un condón consigo en este momento?",
      "intensidad": 3
    },
    {
      "texto": "¿A quién de aquí le gustaría más el bondage?",
      "intensidad": 3
    },
    {
      "texto": "¿Quién tendría sexo en una psicina?",
      "intensidad": 3
    },
    {
      "texto": "¿Quién tendría sexo en la cama de sus papás?",
      "intensidad": 3
    },
    {
      "texto": "¿Quién mentiría sobre su edad en una cita?",
      "intensidad": 3
    },
    {
      "texto": "¿Quién iniciaría una relación para causarle celos a su crush?",
      "intensidad": 3
    }
  ]
}
